setup.py
addr_seeker/HTMLreader.py
addr_seeker/__init__.py
addr_seeker/addr_seeker.py
addr_seeker.egg-info/PKG-INFO
addr_seeker.egg-info/SOURCES.txt
addr_seeker.egg-info/dependency_links.txt
addr_seeker.egg-info/not-zip-safe
addr_seeker.egg-info/top_level.txt