Metadata-Version: 1.0
Name: addr-seeker
Version: 1.0
Summary: searchers a website or a string for a us postal address and parses it.
Home-page: http://github.com/sherifEwis/addr_seeker/
Author: sherif eweis
Author-email: sherifewis@tickletock.com
License: MIT
Platform: UNKNOWN
